i18n_json.cp310-win_amd64.pyd
i18n_json/Exceptions.py
i18n_json/__init__.py
i18n_json/i18n_json.py
i18n_json-0.0.9.dist-info/LICENSE
i18n_json-0.0.9.dist-info/METADATA
i18n_json-0.0.9.dist-info/WHEEL
i18n_json-0.0.9.dist-info/top_level.txt
i18n_json-0.0.9.dist-info/RECORD
