Metadata-Version: 2.1
Name: i18n_json
Version: 0.0.9
Summary: Sychronized, streaming dictionary that uses shared memory as a backend
Home-page: https://github.com/wanghaisheng/json-dict-in-memory
Author: wanghaisheng
Author-email: admin@tiktokastudio.com
Requires-Python: >=3.8
License-File: LICENSE
